README.md
setup.cfg
setup.py
smansaancol/__init__.py
smansaancol/__version__.py
smansaancol/exceptions.py
smansaancol/materi.py
smansaancol/utils.py
smansaancol.egg-info/PKG-INFO
smansaancol.egg-info/SOURCES.txt
smansaancol.egg-info/dependency_links.txt
smansaancol.egg-info/requires.txt
smansaancol.egg-info/top_level.txt