Metadata-Version: 2.1
Name: smansaancol
Version: 0.0.1
Summary: Scraping Web Elearning SMA N 1 Muara Ancalong
Home-page: https://github.com/MR-X-Junior/smansaancol
Author: Rahmat adha
Author-email: rahmadadha11@gmail.com
License: MIT
Keywords: elearning,elearning-scraper,elearning-cbt-scraper
Classifier: Development Status :: 3 - Alpha
Classifier: Intended Audience :: Developers
Classifier: Topic :: Software Development :: Build Tools
Classifier: License :: OSI Approved :: MIT License
Classifier: Natural Language :: Indonesian
Classifier: Programming Language :: Python :: 3
Classifier: Programming Language :: Python :: 3.7
Classifier: Programming Language :: Python :: 3.8
Classifier: Programming Language :: Python :: 3.9
Classifier: Programming Language :: Python :: 3.10
Classifier: Programming Language :: Python :: 3.11
Classifier: Programming Language :: Python :: 3 :: Only
Requires-Python: >=3.7
